stark/__init__.py
stark/agent.py
stark/function.py
stark/llm.py
stark/logger.py
stark/mcp.py
stark/runner.py
stark/skill.py
stark/stark_tool.py
stark/tool.py
stark/type.py
stark/util.py
stark/llm_providers/__init__.py
stark/llm_providers/litellm.py
stark/llm_providers/provider.py
stark/mcp_servers/__init__.py
stark/mcp_servers/stdio.py
stark/tools/__init__.py
stark/tools/code/__init__.py
stark/tools/code/approvals.py
stark/tools/code/code_tool.py
stark/tools/code/utils.py
stark_agents-0.2.4.dist-info/METADATA
stark_agents-0.2.4.dist-info/WHEEL
stark_agents-0.2.4.dist-info/licenses/LICENSE
stark_agents-0.2.4.dist-info/RECORD
