Metadata-Version: 2.3
Name: stark-agents
Version: 0.2.4
Summary: A powerful Python ADK for building model agnostic AI agents
Project-URL: Homepage, https://github.com/dev-aliraza/stark-agents
Project-URL: Repository, https://github.com/dev-aliraza/stark-agents
Project-URL: Issues, https://github.com/dev-aliraza/stark-agents/issues
Author-email: Ali Raza <dev.aliraza@gmail.com>
License: Apache-2.0
Keywords: AI,agent,ai agent,asynchronous,framework,tasks
Classifier: Intended Audience :: Developers
Classifier: License :: OSI Approved :: Apache Software License
Classifier: Operating System :: MacOS
Classifier: Operating System :: Microsoft :: Windows
Classifier: Operating System :: OS Independent
Classifier: Operating System :: POSIX
Classifier: Operating System :: POSIX :: Linux
Classifier: Programming Language :: Python :: 3.12
Classifier: Programming Language :: Python :: 3.13
Classifier: Programming Language :: Python :: 3.14
Classifier: Topic :: Software Development :: Libraries :: Python Modules
Classifier: Typing :: Typed
Requires-Python: >=3.10
Requires-Dist: litellm==1.81.5
Requires-Dist: mcp==1.25.0
Provides-Extra: dev
Requires-Dist: pytest; extra == 'dev'
Requires-Dist: pytest-asyncio; extra == 'dev'
